ogadf_schema/__init__.py
ogadf_schema/common_headers.py
ogadf_schema/events.py
ogadf_schema/irfs.py
ogadf_schema-0.2.4.post1.dist-info/LICENSE
ogadf_schema-0.2.4.post1.dist-info/WHEEL
ogadf_schema-0.2.4.post1.dist-info/METADATA
ogadf_schema-0.2.4.post1.dist-info/RECORD
